{"1":{"id":"1","parent":"#","text":"Art & Culture!!","icon":"","li_attr":{},"a_attr":{},"type":"code","script":"n.n.n.n.,mn.,mn.,m.,","sort":2,"description":{"ops":[{"insert":"\n"}]},"found":true},"3":{"id":"3","parent":"#","text":"Destinations","icon":"","li_attr":{},"a_attr":{},"type":"code","script":"ghjkhgkjgk","sort":0,"description":{"ops":[{"insert":"\n"}]},"found":true},"7":{"id":"7","parent":"1","text":"Cutural","icon":"","li_attr":{},"a_attr":{},"type":"code","sort":0,"script":"","description":{"ops":[{"insert":"\n"}]},"found":true},"fc0dc005-3589-4a24-a449-6d6489b538fe":{"parent":"7","text":"New Component","hist":[{"username":"admin","ds":"2023-09-13T19:10:14.359Z","fromId":"244bcdf5-c6c3-40d2-9eb4-c36fab5eaf64"}],"sort":0,"id":"fc0dc005-3589-4a24-a449-6d6489b538fe","script":"ls -l","description":{"ops":[{"insert":"ls\n"}]},"type":"code","found":true},"5d19476a-c2bc-4a30-af4d-8a878ad144dd":{"parent":"fc0dc005-3589-4a24-a449-6d6489b538fe","text":"New b","hist":[{"username":"admin","ds":"2023-09-13T19:12:56.498Z","fromId":"244bcdf5-c6c3-40d2-9eb4-c36fab5eaf64"}],"sort":1,"id":"5d19476a-c2bc-4a30-af4d-8a878ad144dd","script":"bbbbbbbbhgjhj","type":"code","description":{"ops":[{"insert":"\n"}]},"found":true},"9c8d7f01-ef6d-456b-862d-44e70c840a96":{"parent":"fc0dc005-3589-4a24-a449-6d6489b538fe","text":"New aaaa","hist":[{"username":"admin","ds":"2023-09-13T19:13:20.831Z","fromId":"244bcdf5-c6c3-40d2-9eb4-c36fab5eaf64"}],"sort":0,"id":"9c8d7f01-ef6d-456b-862d-44e70c840a96","script":"# hgfhffhj\nls -l\nls -l\nls -l\nwhoami\n","description":{"ops":[{"insert":"mnbmb,mnb\n"}]},"type":"code","found":true},"5aa7098c-53ca-48e1-8227-a43711a5b75f":{"text":"New Component","parent":"#","script":"","id":"5aa7098c-53ca-48e1-8227-a43711a5b75f","sort":1,"type":"code","description":{"ops":[{"insert":"\n"}]},"found":true},"76205dcf-5705-4488-9cd6-d1bd2b08e8b2":{"text":"New Component","parent":"9c8d7f01-ef6d-456b-862d-44e70c840a96","script":"","id":"76205dcf-5705-4488-9cd6-d1bd2b08e8b2","type":"code","description":{"ops":[{"insert":"\n"}]},"found":true,"sort":1}}